setup.py
python_digits/Digit.py
python_digits/DigitWord.py
python_digits/DigitWordAnalysis.py
python_digits/HexDigit.py
python_digits/__init__.py
python_digits/helpers.py
python_digits.egg-info/PKG-INFO
python_digits.egg-info/SOURCES.txt
python_digits.egg-info/dependency_links.txt
python_digits.egg-info/not-zip-safe
python_digits.egg-info/top_level.txt