Metadata-Version: 1.0
Name: python-digits
Version: 2.0
Summary: Python digits (integers between 0 and 9)
Home-page: https://github.com/dsandersAzure/python_digits
Author: David Sanders
Author-email: dsanderscanadanospam@gmail.com
License: Apache License 2.0
Platform: UNKNOWN
